smartmca/__init__.py
smartmca/smartmca.py
smartmca/test.py
smartmca-0.0.4.dist-info/METADATA
smartmca-0.0.4.dist-info/WHEEL
smartmca-0.0.4.dist-info/licenses/LICENSE
smartmca-0.0.4.dist-info/RECORD
