Metadata-Version: 2.1
Name: smartmca
Version: 0.0.4
Summary: Smart MCA for DT5771 Python Library
Project-URL: Homepage, https://github.com/NuclearInstruments/libSmartMCA
Project-URL: Bug Tracker, https://github.com/NuclearInstruments/libSmartMCA/issues
Author-email: Andrea Abba <abba@nuclearinstruments.eu>
License-File: LICENSE
Keywords: CAEN,MCA,Nuclear Instruments,firmware,fpga
Classifier: License :: OSI Approved :: MIT License
Classifier: Operating System :: OS Independent
Classifier: Programming Language :: Python :: 3
Requires-Python: >=3.5
